{
	"class" : {
		 },
	"instance" : {
		"clicked" : "ls 5/29/2013 16:53:05.594",
		"dimmedForm" : "ls 5/29/2013 16:07:56.366",
		"dimmedForm:" : "ls 5/29/2013 16:07:49.228",
		"enabled" : "ls 5/29/2013 16:55:20.355",
		"enabled:" : "ls 5/29/2013 16:52:06.335",
		"form:" : "ls 5/29/2013 16:23:50.176",
		"initialize" : "ls 7/31/2013 11:44:47.277",
		"initializeSignals" : "ls 7/31/2013 11:44:29.833",
		"onMouseEntered" : "ls 7/31/2013 11:43:55.222",
		"onMouseLeft" : "ls 7/31/2013 11:43:59.941",
		"originalForm" : "ls 5/29/2013 16:14:13.312",
		"originalForm:" : "ls 5/29/2013 16:14:25.368" } }
